aicage/__init__.py
aicage/__main__.py
aicage/_lists.py
aicage/_logging.py
aicage/_version.py
aicage/cli_types.py
aicage/constants.py
aicage/errors.py
aicage/paths.py
aicage/cli/__init__.py
aicage/cli/_errors.py
aicage/cli/_parse.py
aicage/cli/_print_config.py
aicage/cli/entrypoint.py
aicage/config/__init__.py
aicage/config/_file_locking.py
aicage/config/_schema_validation.py
aicage/config/_yaml.py
aicage/config/config_store.py
aicage/config/context.py
aicage/config/errors.py
aicage/config/extended_images.py
aicage/config/image_refs.py
aicage/config/project_config.py
aicage/config/resources.py
aicage/config/runtime_config.py
aicage/config/yaml_loader.py
aicage/config/agent/__init__.py
aicage/config/agent/_custom_loader.py
aicage/config/agent/_metadata.py
aicage/config/agent/_validation.py
aicage/config/agent/loader.py
aicage/config/agent/models.py
aicage/config/base/__init__.py
aicage/config/base/_custom_loader.py
aicage/config/base/_validation.py
aicage/config/base/filter.py
aicage/config/base/loader.py
aicage/config/base/models.py
aicage/config/extensions/__init__.py
aicage/config/extensions/_validation.py
aicage/config/extensions/loader.py
aicage/docker/__init__.py
aicage/docker/_client.py
aicage/docker/_registry_api.py
aicage/docker/_timeouts.py
aicage/docker/build.py
aicage/docker/errors.py
aicage/docker/pull.py
aicage/docker/query.py
aicage/docker/run.py
aicage/docker/types.py
aicage/registry/__init__.py
aicage/registry/_errors.py
aicage/registry/_image_pull.py
aicage/registry/_layers.py
aicage/registry/_logs.py
aicage/registry/_pull_decision.py
aicage/registry/_sanitize.py
aicage/registry/_time.py
aicage/registry/ensure_image.py
aicage/registry/agent_version/__init__.py
aicage/registry/agent_version/_command.py
aicage/registry/agent_version/_images.py
aicage/registry/agent_version/_store.py
aicage/registry/agent_version/checker.py
aicage/registry/digest/__init__.py
aicage/registry/digest/_auth.py
aicage/registry/digest/_docker_io.py
aicage-0.8.17.dist-info/METADATA
aicage-0.8.17.dist-info/WHEEL
aicage-0.8.17.dist-info/entry_points.txt
aicage-0.8.17.dist-info/licenses/LICENSE
aicage-0.8.17.dist-info/RECORD
