Metadata-Version: 2.4
Name: aicage
Version: 0.8.17
Summary: Runs agentic coding assistants in docker containers
Author: Stefan Kuhn
License:                                  Apache License
License-File: LICENSE
Requires-Python: >=3.10
Requires-Dist: docker
Requires-Dist: portalocker
Requires-Dist: pyyaml
